odoo/addons/sale_order_line_initial_quantity/README.rst
odoo/addons/sale_order_line_initial_quantity/__init__.py
odoo/addons/sale_order_line_initial_quantity/__manifest__.py
odoo/addons/sale_order_line_initial_quantity/i18n/sale_order_line_initial_quantity.pot
odoo/addons/sale_order_line_initial_quantity/models/__init__.py
odoo/addons/sale_order_line_initial_quantity/models/sale_order.py
odoo/addons/sale_order_line_initial_quantity/models/sale_order_line.py
odoo/addons/sale_order_line_initial_quantity/readme/CONFIGURE.rst
odoo/addons/sale_order_line_initial_quantity/readme/CONTRIBUTORS.rst
odoo/addons/sale_order_line_initial_quantity/readme/DESCRIPTION.rst
odoo/addons/sale_order_line_initial_quantity/readme/USAGE.rst
odoo/addons/sale_order_line_initial_quantity/static/description/icon.png
odoo/addons/sale_order_line_initial_quantity/static/description/index.html
odoo/addons/sale_order_line_initial_quantity/tests/__init__.py
odoo/addons/sale_order_line_initial_quantity/tests/test_sale_order_line_initial_quantity.py
odoo/addons/sale_order_line_initial_quantity/views/sale.xml
odoo14_addon_sale_order_line_initial_quantity-14.0.1.0.1.dist-info/METADATA
odoo14_addon_sale_order_line_initial_quantity-14.0.1.0.1.dist-info/WHEEL
odoo14_addon_sale_order_line_initial_quantity-14.0.1.0.1.dist-info/top_level.txt
odoo14_addon_sale_order_line_initial_quantity-14.0.1.0.1.dist-info/RECORD
